{
    "training": true,
    "tour": "tdf",
    "year": "2024",
    "features": [
        "distance",
        "elevation",
        "time_delta"
    ],
    "target": "time",
    "models": {
        "linear_regression": {
            "hyperparameters": null,
            "param_grid": null
        },
        "linearsvr": {
            "hyperparameters": {
                "gamma": 3
            },
            "param_grid": {
                "gamma": [
                    3,
                    5,
                    8
                ]
            }
        }
    }
}
