[{"training": true, "tour": "giro", "year": [2023], "features": ["distance", "vertical", "grade", "time_delta"], "target": "time", "models": {"linear_regression": {"hyperparameters": null}, "random_forest_regressor": {"hyperparameters": {"min_samples_leaf": 2, "n_estimators": 600}}, "xgboost": {"hyperparameters": {"learning_rate": 0.1, "max_depth": 5, "n_estimators": 300}}, "linearsvr": {"hyperparameters": {"gamma": 3}}}, "strava_id": 1808024}, {"training": true, "tour": "giro", "year": [2023], "features": ["distance", "vertical", "grade", "time_delta"], "target": "time", "models": {"linear_regression": {"hyperparameters": null}, "random_forest_regressor": {"hyperparameters": {"min_samples_leaf": 2, "n_estimators": 300}}, "xgboost": {"hyperparameters": {"learning_rate": 0.1, "max_depth": 3, "n_estimators": 400}}, "linearsvr": {"hyperparameters": {"gamma": 8}}}, "strava_id": 1821678}, {"training": true, "tour": "giro", "year": [2023], "features": ["distance", "vertical", "grade", "time_delta"], "target": "time", "models": {"linear_regression": {"hyperparameters": null}, "random_forest_regressor": {"hyperparameters": {"min_samples_leaf": 3, "n_estimators": 300}}, "xgboost": {"hyperparameters": {"learning_rate": 0.1, "max_depth": 3, "n_estimators": 300}}, "linearsvr": {"hyperparameters": {"gamma": 3}}}, "strava_id": 3416738}, {"training": true, "tour": "giro", "year": [2023], "features": ["distance", "vertical", "grade", "time_delta"], "target": "time", "models": {"linear_regression": {"hyperparameters": null}, "random_forest_regressor": {"hyperparameters": {"min_samples_leaf": 2, "n_estimators": 600}}, "xgboost": {"hyperparameters": {"learning_rate": 0.1, "max_depth": 3, "n_estimators": 300}}, "linearsvr": {"hyperparameters": {"gamma": 3}}}, "strava_id": 7310716}, {"training": true, "tour": "giro", "year": [2023], "features": ["distance", "vertical", "grade", "time_delta"], "target": "time", "models": {"linear_regression": {"hyperparameters": null}, "random_forest_regressor": {"hyperparameters": {"min_samples_leaf": 2, "n_estimators": 400}}, "xgboost": {"hyperparameters": {"learning_rate": 0.1, "max_depth": 3, "n_estimators": 500}}, "linearsvr": {"hyperparameters": {"gamma": 3}}}, "strava_id": 2676267}, {"training": true, "tour": "giro", "year": [2023], "features": ["distance", "vertical", "grade", "time_delta"], "target": "time", "models": {"linear_regression": {"hyperparameters": null}, "random_forest_regressor": {"hyperparameters": {"min_samples_leaf": 2, "n_estimators": 600}}, "xgboost": {"hyperparameters": {"learning_rate": 0.1, "max_depth": 3, "n_estimators": 500}}, "linearsvr": {"hyperparameters": {"gamma": 3}}}, "strava_id": 4057312}, {"training": true, "tour": "giro", "year": [2023], "features": ["distance", "vertical", "grade", "time_delta"], "target": "time", "models": {"linear_regression": {"hyperparameters": null}, "random_forest_regressor": {"hyperparameters": {"min_samples_leaf": 2, "n_estimators": 600}}, "xgboost": {"hyperparameters": {"learning_rate": 0.1, "max_depth": 5, "n_estimators": 300}}, "linearsvr": {"hyperparameters": {"gamma": 3}}}, "strava_id": 1850959}, {"training": true, "tour": "giro", "year": [2023], "features": ["distance", "vertical", "grade", "time_delta"], "target": "time", "models": {"linear_regression": {"hyperparameters": null}, "random_forest_regressor": {"hyperparameters": {"min_samples_leaf": 2, "n_estimators": 600}}, "xgboost": {"hyperparameters": {"learning_rate": 0.1, "max_depth": 3, "n_estimators": 300}}, "linearsvr": {"hyperparameters": {"gamma": 3}}}, "strava_id": 2905866}, {"training": true, "tour": "giro", "year": [2023], "features": ["distance", "vertical", "grade", "time_delta"], "target": "time", "models": {"linear_regression": {"hyperparameters": null}, "random_forest_regressor": {"hyperparameters": {"min_samples_leaf": 3, "n_estimators": 600}}, "xgboost": {"hyperparameters": {"learning_rate": 0.1, "max_depth": 3, "n_estimators": 400}}, "linearsvr": {"hyperparameters": {"gamma": 3}}}, "strava_id": 12772912}, {"training": true, "tour": "giro", "year": [2023], "features": ["distance", "vertical", "grade", "time_delta"], "target": "time", "models": {"linear_regression": {"hyperparameters": null}, "random_forest_regressor": {"hyperparameters": {"min_samples_leaf": 3, "n_estimators": 400}}, "xgboost": {"hyperparameters": {"learning_rate": 0.01, "max_depth": 5, "n_estimators": 500}}, "linearsvr": {"hyperparameters": {"gamma": 3}}}, "strava_id": 13125039}, {"training": true, "tour": "giro", "year": [2023], "features": ["distance", "vertical", "grade", "time_delta"], "target": "time", "models": {"linear_regression": {"hyperparameters": null}, "random_forest_regressor": {"hyperparameters": {"min_samples_leaf": 2, "n_estimators": 400}}, "xgboost": {"hyperparameters": {"learning_rate": 0.1, "max_depth": 3, "n_estimators": 500}}, "linearsvr": {"hyperparameters": {"gamma": 3}}}, "strava_id": 1751647}, {"training": true, "tour": "giro", "year": [2023], "features": ["distance", "vertical", "grade", "time_delta"], "target": "time", "models": {"linear_regression": {"hyperparameters": null}, "random_forest_regressor": {"hyperparameters": {"min_samples_leaf": 2, "n_estimators": 600}}, "xgboost": {"hyperparameters": {"learning_rate": 0.1, "max_depth": 3, "n_estimators": 500}}, "linearsvr": {"hyperparameters": {"gamma": 3}}}, "strava_id": 2192184}, {"training": true, "tour": "giro", "year": [2023], "features": ["distance", "vertical", "grade", "time_delta"], "target": "time", "models": {"linear_regression": {"hyperparameters": null}, "random_forest_regressor": {"hyperparameters": {"min_samples_leaf": 2, "n_estimators": 400}}, "xgboost": {"hyperparameters": {"learning_rate": 0.1, "max_depth": 3, "n_estimators": 400}}, "linearsvr": {"hyperparameters": {"gamma": 3}}}, "strava_id": 13248583}, {"training": true, "tour": "giro", "year": [2023], "features": ["distance", "vertical", "grade", "time_delta"], "target": "time", "models": {"linear_regression": {"hyperparameters": null}, "random_forest_regressor": {"hyperparameters": {"min_samples_leaf": 2, "n_estimators": 600}}, "xgboost": {"hyperparameters": {"learning_rate": 0.1, "max_depth": 5, "n_estimators": 300}}, "linearsvr": {"hyperparameters": {"gamma": 3}}}, "strava_id": 1847503}, {"training": true, "tour": "giro", "year": [2023], "features": ["distance", "vertical", "grade", "time_delta"], "target": "time", "models": {"linear_regression": {"hyperparameters": null}, "random_forest_regressor": {"hyperparameters": {"min_samples_leaf": 2, "n_estimators": 300}}, "xgboost": {"hyperparameters": {"learning_rate": 0.1, "max_depth": 3, "n_estimators": 500}}, "linearsvr": {"hyperparameters": {"gamma": 3}}}, "strava_id": 1126469}, {"training": true, "tour": "giro", "year": [2023], "features": ["distance", "vertical", "grade", "time_delta"], "target": "time", "models": {"linear_regression": {"hyperparameters": null}, "random_forest_regressor": {"hyperparameters": {"min_samples_leaf": 2, "n_estimators": 400}}, "xgboost": {"hyperparameters": {"learning_rate": 0.1, "max_depth": 5, "n_estimators": 300}}, "linearsvr": {"hyperparameters": {"gamma": 3}}}, "strava_id": 12274527}, {"training": true, "tour": "giro", "year": [2023], "features": ["distance", "vertical", "grade", "time_delta"], "target": "time", "models": {"linear_regression": {"hyperparameters": null}, "random_forest_regressor": {"hyperparameters": {"min_samples_leaf": 2, "n_estimators": 400}}, "xgboost": {"hyperparameters": {"learning_rate": 0.1, "max_depth": 3, "n_estimators": 300}}, "linearsvr": {"hyperparameters": {"gamma": 3}}}, "strava_id": 254096}, {"training": true, "tour": "giro", "year": [2023], "features": ["distance", "vertical", "grade", "time_delta"], "target": "time", "models": {"linear_regression": {"hyperparameters": null}, "random_forest_regressor": {"hyperparameters": {"min_samples_leaf": 2, "n_estimators": 400}}, "xgboost": {"hyperparameters": {"learning_rate": 0.1, "max_depth": 3, "n_estimators": 400}}, "linearsvr": {"hyperparameters": {"gamma": 3}}}, "strava_id": 2573969}, {"training": true, "tour": "giro", "year": [2023], "features": ["distance", "vertical", "grade", "time_delta"], "target": "time", "models": {"linear_regression": {"hyperparameters": null}, "random_forest_regressor": {"hyperparameters": {"min_samples_leaf": 2, "n_estimators": 300}}, "xgboost": {"hyperparameters": {"learning_rate": 0.1, "max_depth": 3, "n_estimators": 400}}, "linearsvr": {"hyperparameters": {"gamma": 3}}}, "strava_id": 49597893}, {"training": true, "tour": "giro", "year": [2023], "features": ["distance", "vertical", "grade", "time_delta"], "target": "time", "models": {"linear_regression": {"hyperparameters": null}, "random_forest_regressor": {"hyperparameters": {"min_samples_leaf": 3, "n_estimators": 300}}, "xgboost": {"hyperparameters": {"learning_rate": 0.01, "max_depth": 3, "n_estimators": 500}}, "linearsvr": {"hyperparameters": {"gamma": 3}}}, "strava_id": 12607976}, {"training": true, "tour": "giro", "year": [2023], "features": ["distance", "vertical", "grade", "time_delta"], "target": "time", "models": {"linear_regression": {"hyperparameters": null}, "random_forest_regressor": {"hyperparameters": {"min_samples_leaf": 2, "n_estimators": 300}}, "xgboost": {"hyperparameters": {"learning_rate": 0.1, "max_depth": 3, "n_estimators": 500}}, "linearsvr": {"hyperparameters": {"gamma": 3}}}, "strava_id": 276702}, {"training": true, "tour": "giro", "year": [2023], "features": ["distance", "vertical", "grade", "time_delta"], "target": "time", "models": {"linear_regression": {"hyperparameters": null}, "random_forest_regressor": {"hyperparameters": {"min_samples_leaf": 2, "n_estimators": 300}}, "xgboost": {"hyperparameters": {"learning_rate": 0.1, "max_depth": 3, "n_estimators": 300}}, "linearsvr": {"hyperparameters": {"gamma": 3}}}, "strava_id": 3194779}, {"training": true, "tour": "giro", "year": [2023], "features": ["distance", "vertical", "grade", "time_delta"], "target": "time", "models": {"linear_regression": {"hyperparameters": null}, "random_forest_regressor": {"hyperparameters": {"min_samples_leaf": 2, "n_estimators": 400}}, "xgboost": {"hyperparameters": {"learning_rate": 0.1, "max_depth": 3, "n_estimators": 500}}, "linearsvr": {"hyperparameters": {"gamma": 3}}}, "strava_id": 9545283}, {"training": true, "tour": "giro", "year": [2023], "features": ["distance", "vertical", "grade", "time_delta"], "target": "time", "models": {"linear_regression": {"hyperparameters": null}, "random_forest_regressor": {"hyperparameters": {"min_samples_leaf": 2, "n_estimators": 300}}, "xgboost": {"hyperparameters": {"learning_rate": 0.1, "max_depth": 3, "n_estimators": 500}}, "linearsvr": {"hyperparameters": {"gamma": 3}}}, "strava_id": 30466500}, {"training": true, "tour": "giro", "year": [2023], "features": ["distance", "vertical", "grade", "time_delta"], "target": "time", "models": {"linear_regression": {"hyperparameters": null}, "random_forest_regressor": {"hyperparameters": {"min_samples_leaf": 2, "n_estimators": 600}}, "xgboost": {"hyperparameters": {"learning_rate": 0.1, "max_depth": 3, "n_estimators": 300}}, "linearsvr": {"hyperparameters": {"gamma": 3}}}, "strava_id": 9776534}, {"training": true, "tour": "giro", "year": [2023], "features": ["distance", "vertical", "grade", "time_delta"], "target": "time", "models": {"linear_regression": {"hyperparameters": null}, "random_forest_regressor": {"hyperparameters": {"min_samples_leaf": 2, "n_estimators": 400}}, "xgboost": {"hyperparameters": {"learning_rate": 0.1, "max_depth": 3, "n_estimators": 300}}, "linearsvr": {"hyperparameters": {"gamma": 3}}}, "strava_id": 8089198}, {"training": true, "tour": "giro", "year": [2023], "features": ["distance", "vertical", "grade", "time_delta"], "target": "time", "models": {"linear_regression": {"hyperparameters": null}, "random_forest_regressor": {"hyperparameters": {"min_samples_leaf": 2, "n_estimators": 400}}, "xgboost": {"hyperparameters": {"learning_rate": 0.1, "max_depth": 3, "n_estimators": 500}}, "linearsvr": {"hyperparameters": {"gamma": 3}}}, "strava_id": 197359}, {"training": true, "tour": "giro", "year": [2023], "features": ["distance", "vertical", "grade", "time_delta"], "target": "time", "models": {"linear_regression": {"hyperparameters": null}, "random_forest_regressor": {"hyperparameters": {"min_samples_leaf": 3, "n_estimators": 400}}, "xgboost": {"hyperparameters": {"learning_rate": 0.1, "max_depth": 3, "n_estimators": 300}}, "linearsvr": {"hyperparameters": {"gamma": 3}}}, "strava_id": 722861}, {"training": true, "tour": "giro", "year": [2023], "features": ["distance", "vertical", "grade", "time_delta"], "target": "time", "models": {"linear_regression": {"hyperparameters": null}, "random_forest_regressor": {"hyperparameters": {"min_samples_leaf": 2, "n_estimators": 300}}, "xgboost": {"hyperparameters": {"learning_rate": 0.1, "max_depth": 5, "n_estimators": 300}}, "linearsvr": {"hyperparameters": {"gamma": 3}}}, "strava_id": 3068615}, {"training": true, "tour": "giro", "year": [2023], "features": ["distance", "vertical", "grade", "time_delta"], "target": "time", "models": {"linear_regression": {"hyperparameters": null}, "random_forest_regressor": {"hyperparameters": {"min_samples_leaf": 2, "n_estimators": 300}}, "xgboost": {"hyperparameters": {"learning_rate": 0.1, "max_depth": 3, "n_estimators": 500}}, "linearsvr": {"hyperparameters": {"gamma": 3}}}, "strava_id": 39169689}, {"training": true, "tour": "giro", "year": [2023], "features": ["distance", "vertical", "grade", "time_delta"], "target": "time", "models": {"linear_regression": {"hyperparameters": null}, "random_forest_regressor": {"hyperparameters": {"min_samples_leaf": 2, "n_estimators": 400}}, "xgboost": {"hyperparameters": {"learning_rate": 0.1, "max_depth": 3, "n_estimators": 300}}, "linearsvr": {"hyperparameters": {"gamma": 3}}}, "strava_id": 584854}, {"training": true, "tour": "giro", "year": [2023], "features": ["distance", "vertical", "grade", "time_delta"], "target": "time", "models": {"linear_regression": {"hyperparameters": null}, "random_forest_regressor": {"hyperparameters": {"min_samples_leaf": 2, "n_estimators": 600}}, "xgboost": {"hyperparameters": {"learning_rate": 0.1, "max_depth": 3, "n_estimators": 400}}, "linearsvr": {"hyperparameters": {"gamma": 3}}}, "strava_id": 4084289}, {"training": true, "tour": "giro", "year": [2023], "features": ["distance", "vertical", "grade", "time_delta"], "target": "time", "models": {"linear_regression": {"hyperparameters": null}, "random_forest_regressor": {"hyperparameters": {"min_samples_leaf": 2, "n_estimators": 600}}, "xgboost": {"hyperparameters": {"learning_rate": 0.1, "max_depth": 3, "n_estimators": 500}}, "linearsvr": {"hyperparameters": {"gamma": 3}}}, "strava_id": 6782552}, {"training": true, "tour": "giro", "year": [2023], "features": ["distance", "vertical", "grade", "time_delta"], "target": "time", "models": {"linear_regression": {"hyperparameters": null}, "random_forest_regressor": {"hyperparameters": {"min_samples_leaf": 2, "n_estimators": 400}}, "xgboost": {"hyperparameters": {"learning_rate": 0.1, "max_depth": 5, "n_estimators": 300}}, "linearsvr": {"hyperparameters": {"gamma": 3}}}, "strava_id": 20904837}, {"training": true, "tour": "giro", "year": [2023], "features": ["distance", "vertical", "grade", "time_delta"], "target": "time", "models": {"linear_regression": {"hyperparameters": null}, "random_forest_regressor": {"hyperparameters": {"min_samples_leaf": 2, "n_estimators": 600}}, "xgboost": {"hyperparameters": {"learning_rate": 0.1, "max_depth": 3, "n_estimators": 500}}, "linearsvr": {"hyperparameters": {"gamma": 8}}}, "strava_id": 3125765}, {"training": true, "tour": "giro", "year": [2023], "features": ["distance", "vertical", "grade", "time_delta"], "target": "time", "models": {"linear_regression": {"hyperparameters": null}, "random_forest_regressor": {"hyperparameters": {"min_samples_leaf": 2, "n_estimators": 600}}, "xgboost": {"hyperparameters": {"learning_rate": 0.1, "max_depth": 3, "n_estimators": 300}}, "linearsvr": {"hyperparameters": {"gamma": 3}}}, "strava_id": 12558355}, {"training": true, "tour": "giro", "year": [2023], "features": ["distance", "vertical", "grade", "time_delta"], "target": "time", "models": {"linear_regression": {"hyperparameters": null}, "random_forest_regressor": {"hyperparameters": {"min_samples_leaf": 2, "n_estimators": 300}}, "xgboost": {"hyperparameters": {"learning_rate": 0.1, "max_depth": 3, "n_estimators": 300}}, "linearsvr": {"hyperparameters": {"gamma": 3}}}, "strava_id": 37167909}, {"training": true, "tour": "giro", "year": [2023], "features": ["distance", "vertical", "grade", "time_delta"], "target": "time", "models": {"linear_regression": {"hyperparameters": null}, "random_forest_regressor": {"hyperparameters": {"min_samples_leaf": 2, "n_estimators": 600}}, "xgboost": {"hyperparameters": {"learning_rate": 0.1, "max_depth": 3, "n_estimators": 400}}, "linearsvr": {"hyperparameters": {"gamma": 3}}}, "strava_id": 3574069}, {"training": true, "tour": "giro", "year": [2023], "features": ["distance", "vertical", "grade", "time_delta"], "target": "time", "models": {"linear_regression": {"hyperparameters": null}, "random_forest_regressor": {"hyperparameters": {"min_samples_leaf": 2, "n_estimators": 400}}, "xgboost": {"hyperparameters": {"learning_rate": 0.1, "max_depth": 7, "n_estimators": 300}}, "linearsvr": {"hyperparameters": {"gamma": 3}}}, "strava_id": 2542098}, {"training": true, "tour": "giro", "year": [2023], "features": ["distance", "vertical", "grade", "time_delta"], "target": "time", "models": {"linear_regression": {"hyperparameters": null}, "random_forest_regressor": {"hyperparameters": {"min_samples_leaf": 2, "n_estimators": 400}}, "xgboost": {"hyperparameters": {"learning_rate": 0.1, "max_depth": 3, "n_estimators": 500}}, "linearsvr": {"hyperparameters": {"gamma": 3}}}, "strava_id": 16571022}, {"training": true, "tour": "giro", "year": [2023], "features": ["distance", "vertical", "grade", "time_delta"], "target": "time", "models": {"linear_regression": {"hyperparameters": null}, "random_forest_regressor": {"hyperparameters": {"min_samples_leaf": 5, "n_estimators": 300}}, "xgboost": {"hyperparameters": {"learning_rate": 0.01, "max_depth": 3, "n_estimators": 500}}, "linearsvr": {"hyperparameters": {"gamma": 3}}}, "strava_id": 3123001}, {"training": true, "tour": "giro", "year": [2023], "features": ["distance", "vertical", "grade", "time_delta"], "target": "time", "models": {"linear_regression": {"hyperparameters": null}, "random_forest_regressor": {"hyperparameters": {"min_samples_leaf": 3, "n_estimators": 300}}, "xgboost": {"hyperparameters": {"learning_rate": 0.1, "max_depth": 3, "n_estimators": 300}}, "linearsvr": {"hyperparameters": {"gamma": 3}}}, "strava_id": 77293819}, {"training": true, "tour": "giro", "year": [2023], "features": ["distance", "vertical", "grade", "time_delta"], "target": "time", "models": {"linear_regression": {"hyperparameters": null}, "random_forest_regressor": {"hyperparameters": {"min_samples_leaf": 2, "n_estimators": 400}}, "xgboost": {"hyperparameters": {"learning_rate": 0.1, "max_depth": 3, "n_estimators": 300}}, "linearsvr": {"hyperparameters": {"gamma": 3}}}, "strava_id": 3423315}, {"training": true, "tour": "giro", "year": [2023], "features": ["distance", "vertical", "grade", "time_delta"], "target": "time", "models": {"linear_regression": {"hyperparameters": null}, "random_forest_regressor": {"hyperparameters": {"min_samples_leaf": 2, "n_estimators": 600}}, "xgboost": {"hyperparameters": {"learning_rate": 0.1, "max_depth": 3, "n_estimators": 500}}, "linearsvr": {"hyperparameters": {"gamma": 3}}}, "strava_id": 5571896}, {"training": true, "tour": "giro", "year": [2023], "features": ["distance", "vertical", "grade", "time_delta"], "target": "time", "models": {"linear_regression": {"hyperparameters": null}, "random_forest_regressor": {"hyperparameters": {"min_samples_leaf": 2, "n_estimators": 600}}, "xgboost": {"hyperparameters": {"learning_rate": 0.1, "max_depth": 3, "n_estimators": 400}}, "linearsvr": {"hyperparameters": {"gamma": 3}}}, "strava_id": 1936233}, {"training": true, "tour": "giro", "year": [2023], "features": ["distance", "vertical", "grade", "time_delta"], "target": "time", "models": {"linear_regression": {"hyperparameters": null}, "random_forest_regressor": {"hyperparameters": {"min_samples_leaf": 2, "n_estimators": 600}}, "xgboost": {"hyperparameters": {"learning_rate": 0.1, "max_depth": 3, "n_estimators": 400}}, "linearsvr": {"hyperparameters": {"gamma": 3}}}, "strava_id": 2413208}, {"training": true, "tour": "giro", "year": [2023], "features": ["distance", "vertical", "grade", "time_delta"], "target": "time", "models": {"linear_regression": {"hyperparameters": null}, "random_forest_regressor": {"hyperparameters": {"min_samples_leaf": 5, "n_estimators": 400}}, "xgboost": {"hyperparameters": {"learning_rate": 0.01, "max_depth": 3, "n_estimators": 500}}, "linearsvr": {"hyperparameters": {"gamma": 3}}}, "strava_id": 1993533}, {"training": true, "tour": "giro", "year": [2023], "features": ["distance", "vertical", "grade", "time_delta"], "target": "time", "models": {"linear_regression": {"hyperparameters": null}, "random_forest_regressor": {"hyperparameters": {"min_samples_leaf": 2, "n_estimators": 600}}, "xgboost": {"hyperparameters": {"learning_rate": 0.01, "max_depth": 3, "n_estimators": 500}}, "linearsvr": {"hyperparameters": {"gamma": 3}}}, "strava_id": 1123635}, {"training": true, "tour": "giro", "year": [2023], "features": ["distance", "vertical", "grade", "time_delta"], "target": "time", "models": {"linear_regression": {"hyperparameters": null}, "random_forest_regressor": {"hyperparameters": {"min_samples_leaf": 2, "n_estimators": 600}}, "xgboost": {"hyperparameters": {"learning_rate": 0.01, "max_depth": 3, "n_estimators": 500}}, "linearsvr": {"hyperparameters": {"gamma": 3}}}, "strava_id": 1754389}, {"training": true, "tour": "giro", "year": [2023], "features": ["distance", "vertical", "grade", "time_delta"], "target": "time", "models": {"linear_regression": {"hyperparameters": null}, "random_forest_regressor": {"hyperparameters": {"min_samples_leaf": 2, "n_estimators": 600}}, "xgboost": {"hyperparameters": {"learning_rate": 0.1, "max_depth": 3, "n_estimators": 500}}, "linearsvr": {"hyperparameters": {"gamma": 3}}}, "strava_id": 240775}, {"training": true, "tour": "giro", "year": [2023], "features": ["distance", "vertical", "grade", "time_delta"], "target": "time", "models": {"linear_regression": {"hyperparameters": null}, "random_forest_regressor": {"hyperparameters": {"min_samples_leaf": 2, "n_estimators": 400}}, "xgboost": {"hyperparameters": {"learning_rate": 0.1, "max_depth": 3, "n_estimators": 500}}, "linearsvr": {"hyperparameters": {"gamma": 3}}}, "strava_id": 33232423}, {"training": true, "tour": "giro", "year": [2023], "features": ["distance", "vertical", "grade", "time_delta"], "target": "time", "models": {"linear_regression": {"hyperparameters": null}, "random_forest_regressor": {"hyperparameters": {"min_samples_leaf": 3, "n_estimators": 400}}, "xgboost": {"hyperparameters": {"learning_rate": 0.1, "max_depth": 3, "n_estimators": 300}}, "linearsvr": {"hyperparameters": {"gamma": 3}}}, "strava_id": 3488983}, {"training": true, "tour": "giro", "year": [2023], "features": ["distance", "vertical", "grade", "time_delta"], "target": "time", "models": {"linear_regression": {"hyperparameters": null}, "random_forest_regressor": {"hyperparameters": {"min_samples_leaf": 2, "n_estimators": 300}}, "xgboost": {"hyperparameters": {"learning_rate": 0.1, "max_depth": 3, "n_estimators": 400}}, "linearsvr": {"hyperparameters": {"gamma": 3}}}, "strava_id": 2566327}, {"training": true, "tour": "giro", "year": [2023], "features": ["distance", "vertical", "grade", "time_delta"], "target": "time", "models": {"linear_regression": {"hyperparameters": null}, "random_forest_regressor": {"hyperparameters": {"min_samples_leaf": 3, "n_estimators": 400}}, "xgboost": {"hyperparameters": {"learning_rate": 0.1, "max_depth": 3, "n_estimators": 300}}, "linearsvr": {"hyperparameters": {"gamma": 3}}}, "strava_id": 21712783}, {"training": true, "tour": "giro", "year": [2023], "features": ["distance", "vertical", "grade", "time_delta"], "target": "time", "models": {"linear_regression": {"hyperparameters": null}, "random_forest_regressor": {"hyperparameters": {"min_samples_leaf": 2, "n_estimators": 600}}, "xgboost": {"hyperparameters": {"learning_rate": 0.1, "max_depth": 3, "n_estimators": 300}}, "linearsvr": {"hyperparameters": {"gamma": 3}}}, "strava_id": 4548902}, {"training": true, "tour": "giro", "year": [2023], "features": ["distance", "vertical", "grade", "time_delta"], "target": "time", "models": {"linear_regression": {"hyperparameters": null}, "random_forest_regressor": {"hyperparameters": {"min_samples_leaf": 3, "n_estimators": 600}}, "xgboost": {"hyperparameters": {"learning_rate": 0.1, "max_depth": 3, "n_estimators": 300}}, "linearsvr": {"hyperparameters": {"gamma": 3}}}, "strava_id": 831403}, {"training": true, "tour": "giro", "year": [2023], "features": ["distance", "vertical", "grade", "time_delta"], "target": "time", "models": {"linear_regression": {"hyperparameters": null}, "random_forest_regressor": {"hyperparameters": {"min_samples_leaf": 3, "n_estimators": 300}}, "xgboost": {"hyperparameters": {"learning_rate": 0.1, "max_depth": 7, "n_estimators": 300}}, "linearsvr": {"hyperparameters": {"gamma": 3}}}, "strava_id": 133606}]
